{"status":"200 OK","result":[{"mid":"/m/06mjl58","id":"/en/science_activities_for_middle_school_students","name":"Science Activities for Middle School Students","notable":{"name":"Book","id":"/book/book"},"lang":"en","score":27.739828},{"mid":"/m/06vs2kh","id":"/en/journal_writing_activities_middle_school","name":"Journal Writing Activities, Middle School","notable":{"name":"Book","id":"/book/book"},"lang":"en","score":8.897779},{"mid":"/m/043rgdd","name":"","lang":"en","score":2.073667},{"mid":"/m/03hp75v","name":"","lang":"en","score":1.597948}],"cost":8,"hits":4}