{"status":"200 OK","result":[{"mid":"/m/01lyv","name":"Country","notable":{"name":"Musical genre","id":"/music/genre"},"lang":"en","score":44.734917},{"mid":"/m/07ssc","id":"/en/united_kingdom","name":"United Kingdom","notable":{"name":"Country","id":"/location/country"},"lang":"en","score":40.856487},{"mid":"/m/032mx","id":"/en/food_and_drug_administration","name":"Food and Drug Administration","notable":{"name":"Government Agency","id":"/government/government_agency"},"lang":"en","score":38.069199},{"mid":"/m/02xwb","id":"/en/fruit","name":"Fruit","notable":{"name":"Food","id":"/food/food"},"lang":"en","score":36.459946},{"mid":"/m/0166b","id":"/en/bosnia_and_herzegovina","name":"Bosnia and Herzegovina","notable":{"name":"Country","id":"/location/country"},"lang":"en","score":35.970322},{"mid":"/m/019rl6","id":"/authority/crunchbase/company/yahoo","name":"Yahoo!","notable":{"name":"Internet Publishing and Broadcasting and Web Search Portals Business","id":"/m/0glj7jy"},"lang":"en","score":35.780102},{"mid":"/m/01c1nm","id":"/en/goa","name":"Goa","notable":{"name":"Indian state","id":"/location/in_state"},"lang":"en","score":35.592281},{"mid":"/m/0kjh","id":"/en/abba","name":"ABBA","notable":{"name":"Soft rock Artist","id":"/m/02k_kn"},"lang":"en","score":35.237762},{"mid":"/m/01w334h","id":"/en/tiesto","name":"Ti\u00ebsto","notable":{"name":"Progressive electronic Artist","id":"/m/02w6s3"},"lang":"en","score":34.354591},{"mid":"/m/041v73","id":"/en/acronym_and_initialism","name":"Acronym","notable":{"name":"Literature Subject","id":"/book/book_subject"},"lang":"en","score":34.273426},{"mid":"/m/0hg5","id":"/en/andorra","name":"Andorra","notable":{"name":"Parliamentary Democracy","id":"/m/018wl5"},"lang":"en","score":34.238384},{"mid":"/m/0kc6x","id":"/en/espn","name":"ESPN","notable":{"name":"TV Network","id":"/tv/tv_network"},"lang":"en","score":34.205494},{"mid":"/m/06j6l","id":"/en/rhythm_and_blues","name":"Rhythm and blues","notable":{"name":"Musical genre","id":"/music/genre"},"lang":"en","score":33.735966},{"mid":"/m/01b7dt","id":"/en/barnes_noble","name":"Barnes & Noble","notable":{"name":"Bookstore Business","id":"/m/02gtkh"},"lang":"en","score":32.789677},{"mid":"/m/07sbbz2","name":"Rock and roll","notable":{"name":"Musical genre","id":"/music/genre"},"lang":"en","score":32.770737},{"mid":"/m/08z129","id":"/en/at_t","name":"AT&T","notable":{"name":"Fixed Network Operator Business","id":"/m/02n_1k5"},"lang":"en","score":32.273838},{"mid":"/m/016k1c","id":"/en/home_and_away","name":"Home and Away","notable":{"name":"TV Soap Opera","id":"/m/06q7n"},"lang":"en","score":32.164558},{"mid":"/m/0fzyg","name":"Aviation","notable":{"name":"Industry","id":"/business/industry"},"lang":"en","score":32.087086},{"mid":"/m/02spfd","id":"/en/deloitte_touche","name":"Deloitte","notable":{"name":"Business Operation","id":"/business/business_operation"},"lang":"en","score":31.764669},{"mid":"/m/09lxtg","id":"/en/trinidad_and_tobago","name":"Trinidad and Tobago","notable":{"name":"Country","id":"/location/country"},"lang":"en","score":31.725262}],"cursor":20,"cost":19,"hits":89664}